{
  "result": "None",
  "parameters": [{
    "bombs": [{
      "Bomb": {
        "location": {
          "IntervalVector": {
            "elements": [{
              "key": "x",
              "value": {
                "Interval": {
                  "lower_bound": 6.379303549489984E-7,
                  "upper_bound": 6.379303549489984E-7
                }
              }
            }]
          }
        },
        "efficiency": 4.069551377653551E-13
      }
    }, {
      "Bomb": {
        "location": {
          "IntervalVector": {
            "elements": [{
              "key": "x",
              "value": {
                "Interval": {
                  "lower_bound": 6.379303549489984E-7,
                  "upper_bound": 6.379303549489984E-7
                }
              }
            }]
          }
        },
        "efficiency": 4.069551377653551E-13
      }
    }, {
      "Bomb": {
        "location": {
          "IntervalVector": {
            "elements": [{
              "key": "x",
              "value": {
                "Interval": {
                  "lower_bound": 0.04845370274309378,
                  "upper_bound": 0.04845370274309378
                }
              }
            }]
          }
        },
        "efficiency": 0.002347761309516094
      }
    }, {
      "Bomb": {
        "location": {
          "IntervalVector": {
            "elements": [{
              "key": "x",
              "value": {
                "Interval": {
                  "lower_bound": 0.05332611502790926,
                  "upper_bound": 0.05332611502790926
                }
              }
            }]
          }
        },
        "efficiency": 0.0028436745439698098
      }
    }, {
      "Bomb": {
        "location": {
          "IntervalVector": {
            "elements": [{
              "key": "x",
              "value": {
                "Interval": {
                  "lower_bound": -0.05620522913984642,
                  "upper_bound": -0.05620522913984642
                }
              }
            }]
          }
        },
        "efficiency": 0.0031590277826626413
      }
    }, {
      "Bomb": {
        "location": {
          "IntervalVector": {
            "elements": [{
              "key": "x",
              "value": {
                "Interval": {
                  "lower_bound": 0.07621496916177117,
                  "upper_bound": 0.07621496916177117
                }
              }
            }]
          }
        },
        "efficiency": 0.005808721524329731
      }
    }, {
      "Bomb": {
        "location": {
          "IntervalVector": {
            "elements": [{
              "key": "x",
              "value": {
                "Interval": {
                  "lower_bound": -0.1488054086617925,
                  "upper_bound": -0.1488054086617925
                }
              }
            }]
          }
        },
        "efficiency": 0.022143049647003074
      }
    }, {
      "Bomb": {
        "location": {
          "IntervalVector": {
            "elements": [{
              "key": "x",
              "value": {
                "Interval": {
                  "lower_bound": -0.15551692399134237,
                  "upper_bound": -0.15551692399134237
                }
              }
            }]
          }
        },
        "efficiency": 0.02418551364772896
      }
    }, {
      "Bomb": {
        "location": {
          "IntervalVector": {
            "elements": [{
              "key": "x",
              "value": {
                "Interval": {
                  "lower_bound": 0.1897980240704489,
                  "upper_bound": 0.1897980240704489
                }
              }
            }]
          }
        },
        "efficiency": 0.036023289941046706
      }
    }, {
      "Bomb": {
        "location": {
          "IntervalVector": {
            "elements": [{
              "key": "x",
              "value": {
                "Interval": {
                  "lower_bound": -0.2020722764129312,
                  "upper_bound": -0.2020722764129312
                }
              }
            }]
          }
        },
        "efficiency": 0.04083320489470407
      }
    }]
  }, {
    "rMax": [{
      "key": "x",
      "value": 1.0
    }, {
      "key": "y",
      "value": 1.0
    }, {
      "key": "z",
      "value": 1.0
    }]
  }, {
    "maxPower": [[{
      "x": 0.0
    }, {
      "y": 0.0
    }, {
      "z": 0.0
    }], [{
      "x": 0.1111111111111111
    }, {
      "y": 0.1111111111111111
    }, {
      "z": 0.1111111111111111
    }], [{
      "x": 0.2222222222222222
    }, {
      "y": 0.2222222222222222
    }, {
      "z": 0.2222222222222222
    }], [{
      "x": 0.3333333333333333
    }, {
      "y": 0.3333333333333333
    }, {
      "z": 0.3333333333333333
    }], [{
      "x": 0.4444444444444444
    }, {
      "y": 0.4444444444444444
    }, {
      "z": 0.4444444444444444
    }], [{
      "x": 0.5555555555555556
    }, {
      "y": 0.5555555555555556
    }, {
      "z": 0.5555555555555556
    }], [{
      "x": 0.6666666666666666
    }, {
      "y": 0.6666666666666666
    }, {
      "z": 0.6666666666666666
    }], [{
      "x": 0.7777777777777778
    }, {
      "y": 0.7777777777777778
    }, {
      "z": 0.7777777777777778
    }], [{
      "x": 0.8888888888888888
    }, {
      "y": 0.8888888888888888
    }, {
      "z": 0.8888888888888888
    }], [{
      "x": 1.0
    }, {
      "y": 1.0
    }, {
      "z": 1.0
    }]]
  }, {
    "startTime": 58055563994846
  }, {
    "maxBombs": 10
  }, {
    "_nodeId": 5
  }]
}